[
    {
        "label": "procrastination (33.00%)",
        "value": 0.27064709259411135
    },
    {
        "label": "mail (27.47%)",
        "value": 0.22529320101697692
    },
    {
        "label": "tv:local (27.08%)",
        "value": 0.22209464446813743
    },
    {
        "label": "write (23.12%)",
        "value": 0.1896169933568441
    },
    {
        "label": "term (11.26%)",
        "value": 0.09234806856393012
    },
    {
        "label": "misc (99.00%)",
        "value": 99.0
    }
]