[
    {
        "color": "hsl(210, 55%, 45%)",
        "label": "code:matlab (4.17%)",
        "value": 3.646061029990382
    },
    {
        "color": "hsl(70, 55%, 45%)",
        "label": "irc (1.88%)",
        "value": 1.6437877065664075
    },
    {
        "color": "hsl(190, 55%, 45%)",
        "label": "mail (11.96%)",
        "value": 10.457287750284166
    },
    {
        "color": "hsl(170, 55%, 45%)",
        "label": "procrastination (59.54%)",
        "value": 52.05910640902335
    },
    {
        "color": "hsl(290, 55%, 45%)",
        "label": "read:pdf (14.78%)",
        "value": 12.922969310133778
    },
    {
        "color": "hsl(130, 55%, 45%)",
        "label": "read:rss (1.88%)",
        "value": 1.6437877065664075
    },
    {
        "color": "hsl(50, 55%, 45%)",
        "label": "term (8.06%)",
        "value": 7.047302614321939
    },
    {
        "color": "hsl(330, 55%, 45%)",
        "label": "tv:local (12.10%)",
        "value": 10.57969747311358
    }
]