[
    {
        "color": "#98df8a",
        "label": "mail (15.44%)",
        "value": 15.44
    },
    {
        "color": "#7f7f7f",
        "label": "misc (9.37%)",
        "value": 9.36999999999999
    },
    {
        "color": "#8c564b",
        "label": "procrastination (33.64%)",
        "value": 33.64
    },
    {
        "color": "#aec7e8",
        "label": "read:rss (1.29%)",
        "value": 1.29
    },
    {
        "color": "#c5b0d5",
        "label": "term (25.00%)",
        "value": 25.0
    },
    {
        "color": "#c7c7c7",
        "label": "tv:local (13.79%)",
        "value": 13.79
    },
    {
        "color": "#d62728",
        "label": "write (1.47%)",
        "value": 1.47
    }
]