{"piedata": [{"color": "#1f77b4", "label": "browsing (35.71%)", "value": 35.71}, {"color": "#d62728", "label": "communities (3.57%)", "value": 3.57}, {"color": "#ff9896", "label": "irc (1.19%)", "value": 1.19}, {"color": "#9467bd", "label": "mail (2.38%)", "value": 2.38}, {"color": "#c5b0d5", "label": "misc (5.95%)", "value": 5.95}, {"color": "#dbdb8d", "label": "tv-web (1.19%)", "value": 1.19}, {"color": "#17becf", "label": "write (50.00%)", "value": 50.0}], "tagdata": {"browsing": {"color": "#1f77b4", "minute": [2, 3, 4, 6, 7, 8, 11, 12, 13, 14, 15, 16, 17, 22, 24, 25, 26, 34, 41, 42]}, "communities": {"color": "#d62728", "minute": [10, 11]}, "irc": {"color": "#ff9896", "minute": [39]}, "mail": {"color": "#9467bd", "minute": [9]}, "misc": {"color": "#c5b0d5", "minute": [36, 37, 38, 39, 40]}, "tv-web": {"color": "#dbdb8d", "minute": [13]}, "write": {"color": "#17becf", "minute": [0, 1, 2, 3, 4, 5, 6, 18, 19, 20, 21, 23, 24, 26, 27, 28, 29, 30, 31, 32, 33, 34, 35, 36, 37, 41]}}}