{"piedata": [{"color": "#1f77b4", "label": "browsing (11.67%)", "value": 11.67}, {"color": "#ffbb78", "label": "code-python (0.83%)", "value": 0.83}, {"color": "#d62728", "label": "communities (15.83%)", "value": 15.83}, {"color": "#9467bd", "label": "mail (4.17%)", "value": 4.17}, {"color": "#c5b0d5", "label": "misc (38.33%)", "value": 38.33}, {"color": "#e377c2", "label": "social (11.67%)", "value": 11.67}, {"color": "#c7c7c7", "label": "tv-web (17.50%)", "value": 17.5}], "tagdata": {"browsing": {"color": "#1f77b4", "minute": [40, 41, 42, 43, 44, 45, 456, 460, 461]}, "code-python": {"color": "#ffbb78", "minute": [60]}, "communities": {"color": "#d62728", "minute": [7, 8, 442, 447, 448, 449, 450, 451, 452, 453, 454, 455]}, "mail": {"color": "#9467bd", "minute": [8, 9, 444, 446]}, "misc": {"color": "#c5b0d5", "minute": [9, 31, 32, 37, 38, 39, 40, 45, 46, 47, 48, 49, 50, 51, 52, 53, 54, 55, 56, 57, 58, 59, 60, 61, 441, 442, 451, 452, 457, 458, 459]}, "social": {"color": "#e377c2", "minute": [2, 3, 37, 38, 42, 51, 59, 443, 445, 446, 457, 458]}, "tv-web": {"color": "#c7c7c7", "minute": [0, 1, 2, 3, 4, 6, 10, 19, 20, 29, 30, 31, 32, 33, 34, 35, 36]}}}