[
    {
        "label": "procrastination (72.41%)",
        "value": 72.41
    },
    {
        "label": "irc (5.75%)",
        "value": 5.75
    },
    {
        "label": "read:rss (4.02%)",
        "value": 4.02
    },
    {
        "label": "mail (4.02%)",
        "value": 4.02
    },
    {
        "label": "write (2.87%)",
        "value": 2.87
    },
    {
        "label": "tv:local (2.30%)",
        "value": 2.3
    },
    {
        "label": "read:pdf (1.15%)",
        "value": 1.15
    },
    {
        "label": "misc (7.48%)",
        "value": 7.480000000000004
    }
]