[
    {
        "color": "#c7c7c7",
        "label": "communities (2.62%)",
        "value": 2.5833169000197205
    },
    {
        "color": "#e377c2",
        "label": "irc (1.41%)",
        "value": 1.3902583316900021
    },
    {
        "color": "#dbdb8d",
        "label": "mail (3.02%)",
        "value": 2.9777164267402885
    },
    {
        "color": "#d62728",
        "label": "read:pdf (8.25%)",
        "value": 8.134490238611715
    },
    {
        "color": "#aec7e8",
        "label": "read:rss (7.44%)",
        "value": 7.335831197002565
    },
    {
        "color": "#ff9896",
        "label": "social (68.01%)",
        "value": 67.05777953066458
    },
    {
        "color": "#1f77b4",
        "label": "term (9.46%)",
        "value": 9.327548806941435
    },
    {
        "color": "#98df8a",
        "label": "write (1.21%)",
        "value": 1.1930585683297181
    }
]