{
    "piedata": [
        {
            "color": "#98df8a",
            "label": "communities (5.18%)",
            "value": 5.18
        },
        {
            "color": "#d62728",
            "label": "irc (4.85%)",
            "value": 4.85
        },
        {
            "color": "#ff9896",
            "label": "mail (1.29%)",
            "value": 1.29
        },
        {
            "color": "#9467bd",
            "label": "misc (46.93%)",
            "value": 46.93
        },
        {
            "color": "#e377c2",
            "label": "read:pdf (27.18%)",
            "value": 27.18
        },
        {
            "color": "#7f7f7f",
            "label": "social (8.58%)",
            "value": 8.58
        },
        {
            "color": "#c7c7c7",
            "label": "term (5.99%)",
            "value": 5.99
        }
    ],
    "tagdata": {
        "communities": {
            "color": "#98df8a",
            "minute": [
                513,
                516,
                517,
                518,
                519,
                520,
                527,
                528,
                795,
                796,
                797,
                920,
                990,
                991,
                992,
                1165,
                1166,
                1167,
                1169,
                1170,
                1202,
                1204,
                1209,
                1210,
                1211,
                1212,
                1213,
                1214,
                1215,
                1248,
                1292,
                1324
            ]
        },
        "irc": {
            "color": "#d62728",
            "minute": [
                529,
                530,
                661,
                667,
                668,
                669,
                670,
                671,
                672,
                816,
                872,
                879,
                923,
                924,
                969,
                970,
                971,
                972,
                973,
                1045,
                1155,
                1227,
                1228,
                1249,
                1250,
                1293,
                1315,
                1337,
                1338,
                1402
            ]
        },
        "mail": {
            "color": "#ff9896",
            "minute": [
                511,
                793,
                798,
                941,
                984,
                1061,
                1073,
                1217
            ]
        },
        "read:pdf": {
            "color": "#e377c2",
            "minute": [
                805,
                817,
                821,
                822,
                826,
                828,
                829,
                830,
                831,
                832,
                837,
                839,
                844,
                847,
                848,
                852,
                853,
                854,
                855,
                857,
                863,
                868,
                869,
                870,
                873,
                874,
                875,
                876,
                877,
                878,
                880,
                881,
                882,
                883,
                884,
                888,
                889,
                894,
                896,
                897,
                898,
                900,
                901,
                902,
                904,
                905,
                906,
                907,
                908,
                909,
                910,
                911,
                912,
                938,
                939,
                940,
                942,
                943,
                944,
                950,
                951,
                952,
                953,
                954,
                957,
                958,
                959,
                960,
                961,
                974,
                975,
                976,
                985,
                987,
                993,
                1023,
                1024,
                1025,
                1026,
                1028,
                1029,
                1030,
                1031,
                1040,
                1046,
                1047,
                1048,
                1049,
                1050,
                1051,
                1052,
                1056,
                1063,
                1065,
                1066,
                1070,
                1079,
                1080,
                1151,
                1219,
                1220,
                1302,
                1303,
                1304,
                1305,
                1306,
                1308,
                1319,
                1320,
                1327,
                1329,
                1330,
                1340,
                1342,
                1344,
                1345,
                1346,
                1347,
                1353,
                1364,
                1365,
                1366,
                1367,
                1368,
                1369,
                1370,
                1371,
                1372,
                1384,
                1385,
                1386,
                1387,
                1388,
                1391,
                1392,
                1393,
                1396,
                1397,
                1398,
                1399,
                1400,
                1401,
                1403,
                1408,
                1409,
                1410,
                1411,
                1412,
                1414,
                1415,
                1416,
                1417,
                1418,
                1419,
                1421,
                1422,
                1423,
                1424,
                1425,
                1426,
                1427,
                1428,
                1429,
                1430,
                1436,
                1437,
                1438,
                1439
            ]
        },
        "social": {
            "color": "#7f7f7f",
            "minute": [
                509,
                510,
                512,
                800,
                801,
                813,
                814,
                815,
                885,
                933,
                934,
                935,
                945,
                956,
                962,
                966,
                986,
                1036,
                1037,
                1038,
                1039,
                1092,
                1095,
                1096,
                1097,
                1102,
                1103,
                1160,
                1209,
                1210,
                1211,
                1212,
                1222,
                1223,
                1224,
                1225,
                1226,
                1236,
                1237,
                1266,
                1267,
                1287,
                1299,
                1300,
                1321,
                1322,
                1349,
                1373,
                1374,
                1375,
                1379,
                1380,
                1404
            ]
        },
        "term": {
            "color": "#c7c7c7",
            "minute": [
                508,
                662,
                663,
                675,
                676,
                677,
                687,
                688,
                698,
                710,
                718,
                721,
                723,
                724,
                737,
                740,
                767,
                768,
                788,
                806,
                807,
                808,
                977,
                978,
                982,
                994,
                1014,
                1081,
                1216,
                1218,
                1221,
                1251,
                1252,
                1256,
                1325,
                1326,
                1354
            ]
        }
    }
}