[
    {
        "color": "#98df8a",
        "label": "irc (2.34%)",
        "value": 2.1745190967382215
    },
    {
        "color": "#9467bd",
        "label": "mail (11.70%)",
        "value": 10.872595483691107
    },
    {
        "color": "#8c564b",
        "label": "procrastination (87.72%)",
        "value": 81.51658767772511
    },
    {
        "color": "#ffbb78",
        "label": "read:pdf (1.46%)",
        "value": 1.3567512312982064
    },
    {
        "color": "#ff9896",
        "label": "term (4.39%)",
        "value": 4.079546510547346
    }
]