[
    {
        "color": "#c49c94",
        "label": "mail (2.43%)",
        "value": 2.43
    },
    {
        "color": "#8c564b",
        "label": "misc (1.89%)",
        "value": 1.8900000000000006
    },
    {
        "color": "#9467bd",
        "label": "procrastination:social (91.64%)",
        "value": 91.64
    },
    {
        "color": "#dbdb8d",
        "label": "read:pdf (1.08%)",
        "value": 1.08
    },
    {
        "color": "#ffbb78",
        "label": "term (2.96%)",
        "value": 2.96
    }
]