[
    {
        "label": "procrastination (53.85%)",
        "value": 0.5347567030784508
    },
    {
        "label": "tv:local (21.85%)",
        "value": 0.2169811320754717
    },
    {
        "label": "irc (15.38%)",
        "value": 0.15273088381330685
    },
    {
        "label": "read:pdf (3.50%)",
        "value": 0.03475670307845084
    },
    {
        "label": "mail (3.50%)",
        "value": 0.03475670307845084
    },
    {
        "label": "read:djvu (1.40%)",
        "value": 0.013902681231380337
    },
    {
        "label": "term (1.22%)",
        "value": 0.012115193644488579
    },
    {
        "label": "misc (99.00%)",
        "value": 99.0
    }
]