[
    {
        "color": "#c5b0d5",
        "label": "mail (4.07%)",
        "value": 4.07
    },
    {
        "color": "#c7c7c7",
        "label": "misc (0.96%)",
        "value": 0.960000000000008
    },
    {
        "color": "#d62728",
        "label": "procrastination (77.71%)",
        "value": 77.71
    },
    {
        "color": "#ff9896",
        "label": "read:pdf (2.33%)",
        "value": 2.33
    },
    {
        "color": "#2ca02c",
        "label": "read:rss (2.33%)",
        "value": 2.33
    },
    {
        "color": "#aec7e8",
        "label": "term (12.60%)",
        "value": 12.6
    }
]