{
    "piedata": [
        {
            "color": "#98df8a",
            "label": "communities (1.61%)",
            "value": 1.61
        },
        {
            "color": "#d62728",
            "label": "irc (9.68%)",
            "value": 9.68
        },
        {
            "color": "#ff9896",
            "label": "mail (7.94%)",
            "value": 7.94
        },
        {
            "color": "#9467bd",
            "label": "misc (33.00%)",
            "value": 33.0
        },
        {
            "color": "#c5b0d5",
            "label": "read:djvu (2.98%)",
            "value": 2.98
        },
        {
            "color": "#e377c2",
            "label": "read:pdf (14.02%)",
            "value": 14.02
        },
        {
            "color": "#7f7f7f",
            "label": "social (11.17%)",
            "value": 11.17
        },
        {
            "color": "#c7c7c7",
            "label": "term (11.29%)",
            "value": 11.29
        },
        {
            "color": "#dbdb8d",
            "label": "tv:local (8.31%)",
            "value": 8.31
        }
    ],
    "tagdata": {
        "code:haskell": {
            "color": "#1f77b4",
            "minute": [
                985
            ]
        },
        "communities": {
            "color": "#98df8a",
            "minute": [
                49,
                533,
                547,
                602,
                603,
                627,
                646,
                647,
                794,
                804,
                805,
                896,
                899
            ]
        },
        "irc": {
            "color": "#d62728",
            "minute": [
                0,
                2,
                5,
                7,
                8,
                9,
                19,
                24,
                29,
                33,
                34,
                35,
                36,
                37,
                503,
                521,
                522,
                609,
                781,
                782,
                795,
                862,
                928,
                932,
                933,
                934,
                936,
                938,
                941,
                942,
                943,
                947,
                952,
                954,
                955,
                957,
                983,
                1011,
                1012,
                1022,
                1027,
                1043,
                1060,
                1066,
                1079,
                1114,
                1117,
                1121,
                1122,
                1124,
                1131,
                1142,
                1155,
                1177,
                1181,
                1182,
                1184,
                1187,
                1195,
                1219,
                1220,
                1221,
                1222,
                1225,
                1226,
                1230,
                1232,
                1248,
                1251,
                1253,
                1279,
                1319,
                1336,
                1339,
                1340,
                1343,
                1346,
                1352
            ]
        },
        "mail": {
            "color": "#ff9896",
            "minute": [
                38,
                58,
                504,
                779,
                784,
                785,
                797,
                898,
                1051,
                1080,
                1081,
                1082,
                1083,
                1084,
                1085,
                1086,
                1087,
                1088,
                1089,
                1090,
                1091,
                1092,
                1093,
                1094,
                1095,
                1096,
                1097,
                1098,
                1099,
                1100,
                1104,
                1105,
                1106,
                1107,
                1132,
                1133,
                1154,
                1156,
                1157,
                1158,
                1159,
                1165,
                1166,
                1167,
                1168,
                1170,
                1171,
                1172,
                1173,
                1183,
                1185,
                1186,
                1188,
                1236,
                1269,
                1270,
                1288,
                1290,
                1291,
                1296,
                1300,
                1415,
                1418,
                1434
            ]
        },
        "read:djvu": {
            "color": "#c5b0d5",
            "minute": [
                13,
                527,
                528,
                529,
                798,
                895,
                902,
                904,
                905,
                906,
                909,
                910,
                911,
                912,
                913,
                914,
                915,
                916,
                917,
                918,
                919,
                968,
                969,
                1378
            ]
        },
        "read:pdf": {
            "color": "#e377c2",
            "minute": [
                17,
                515,
                516,
                518,
                519,
                520,
                523,
                524,
                525,
                526,
                530,
                531,
                532,
                588,
                589,
                590,
                591,
                592,
                593,
                594,
                595,
                596,
                597,
                604,
                605,
                606,
                607,
                613,
                614,
                615,
                617,
                618,
                619,
                620,
                621,
                622,
                623,
                625,
                626,
                638,
                639,
                640,
                641,
                642,
                643,
                799,
                802,
                803,
                824,
                825,
                826,
                832,
                836,
                837,
                838,
                863,
                864,
                865,
                866,
                868,
                869,
                870,
                871,
                874,
                875,
                877,
                878,
                879,
                882,
                883,
                885,
                886,
                890,
                891,
                892,
                893,
                894,
                907,
                908,
                935,
                956,
                958,
                959,
                962,
                963,
                964,
                965,
                966,
                970,
                971,
                972,
                992,
                993,
                1002,
                1005,
                1010,
                1017,
                1018,
                1019,
                1028,
                1029,
                1042,
                1065,
                1119,
                1120,
                1239,
                1281,
                1351,
                1375,
                1377,
                1425,
                1426,
                1437
            ]
        },
        "social": {
            "color": "#7f7f7f",
            "minute": [
                6,
                10,
                55,
                59,
                505,
                506,
                507,
                508,
                509,
                511,
                513,
                587,
                598,
                599,
                601,
                644,
                645,
                650,
                788,
                789,
                790,
                791,
                792,
                808,
                809,
                820,
                821,
                823,
                839,
                855,
                860,
                861,
                887,
                888,
                900,
                920,
                921,
                924,
                995,
                996,
                1006,
                1008,
                1009,
                1015,
                1016,
                1020,
                1054,
                1055,
                1056,
                1058,
                1113,
                1147,
                1193,
                1197,
                1227,
                1271,
                1272,
                1273,
                1280,
                1286,
                1298,
                1299,
                1301,
                1307,
                1308,
                1324,
                1326,
                1329,
                1391,
                1395,
                1397,
                1406,
                1408,
                1410,
                1412,
                1417,
                1419,
                1420,
                1422,
                1423,
                1424,
                1427,
                1428,
                1429,
                1430,
                1431,
                1435,
                1436,
                1438,
                1439
            ]
        },
        "term": {
            "color": "#c7c7c7",
            "minute": [
                12,
                27,
                28,
                60,
                502,
                558,
                608,
                786,
                787,
                927,
                975,
                976,
                977,
                978,
                984,
                989,
                990,
                991,
                994,
                998,
                999,
                1003,
                1004,
                1021,
                1023,
                1024,
                1026,
                1068,
                1069,
                1071,
                1073,
                1074,
                1075,
                1076,
                1077,
                1078,
                1101,
                1116,
                1118,
                1123,
                1126,
                1127,
                1135,
                1136,
                1137,
                1139,
                1140,
                1141,
                1143,
                1144,
                1145,
                1148,
                1149,
                1152,
                1153,
                1160,
                1161,
                1162,
                1163,
                1169,
                1174,
                1175,
                1176,
                1178,
                1179,
                1180,
                1191,
                1196,
                1218,
                1223,
                1233,
                1235,
                1240,
                1241,
                1242,
                1243,
                1244,
                1245,
                1247,
                1249,
                1250,
                1258,
                1259,
                1263,
                1264,
                1302,
                1303,
                1304,
                1305,
                1306,
                1361
            ]
        },
        "tv:local": {
            "color": "#dbdb8d",
            "minute": [
                13,
                527,
                528,
                529,
                798,
                895,
                902,
                904,
                905,
                906,
                909,
                910,
                911,
                912,
                913,
                914,
                915,
                916,
                917,
                918,
                919,
                968,
                969,
                1080,
                1081,
                1082,
                1083,
                1084,
                1085,
                1086,
                1087,
                1088,
                1089,
                1090,
                1091,
                1092,
                1093,
                1094,
                1095,
                1096,
                1097,
                1098,
                1099,
                1100,
                1104,
                1105,
                1106,
                1107,
                1132,
                1133,
                1154,
                1156,
                1157,
                1158,
                1159,
                1165,
                1166,
                1167,
                1170,
                1171,
                1172,
                1173,
                1183,
                1185,
                1186,
                1188,
                1378
            ]
        }
    }
}