[
    {
        "color": "#c7c7c7",
        "label": "communities (4.58%)",
        "value": 4.58
    },
    {
        "color": "#e377c2",
        "label": "irc (1.23%)",
        "value": 1.23
    },
    {
        "color": "#dbdb8d",
        "label": "mail (3.87%)",
        "value": 3.87
    },
    {
        "color": "#bcbd22",
        "label": "misc (2.29%)",
        "value": 2.289999999999992
    },
    {
        "color": "#d62728",
        "label": "read:pdf (6.69%)",
        "value": 6.69
    },
    {
        "color": "#ff9896",
        "label": "social (63.03%)",
        "value": 63.03
    },
    {
        "color": "#1f77b4",
        "label": "term (18.31%)",
        "value": 18.31
    }
]