[
    {
        "color": "hsl(350, 55%, 45%)",
        "label": "code:python (4.26%)",
        "value": 3.7978069002407056
    },
    {
        "color": "hsl(70, 55%, 45%)",
        "label": "irc (1.22%)",
        "value": 1.0876348399750377
    },
    {
        "color": "hsl(190, 55%, 45%)",
        "label": "mail (20.67%)",
        "value": 18.42738700187216
    },
    {
        "color": "hsl(170, 55%, 45%)",
        "label": "procrastination (53.50%)",
        "value": 47.69546224480699
    },
    {
        "color": "hsl(50, 55%, 45%)",
        "label": "term (13.68%)",
        "value": 12.195774271195505
    },
    {
        "color": "hsl(330, 55%, 45%)",
        "label": "tv:local (18.84%)",
        "value": 16.7959347419096
    }
]