[
    {
        "label": "irc (3.16%)",
        "value": 2.2169215658762456
    },
    {
        "label": "mail (42.53%)",
        "value": 29.83723866984706
    },
    {
        "label": "procrastination (42.11%)",
        "value": 29.542584537673637
    },
    {
        "label": "read:pdf (7.58%)",
        "value": 5.317805528272766
    },
    {
        "label": "term (6.95%)",
        "value": 4.8758243300126285
    },
    {
        "label": "tv:local (40.21%)",
        "value": 28.20962536831767
    }
]